{
  "year": 2023,
  "day": 21,
  "level": "second",
  "title": "Step Counter",
  "stars": 1,
  "solution": {
    "first": "3853"
  },
  "input": "...................................................................................................................................\n................#.##....#......#.........#.....#.........................#......................#....#................#............\n....#....#..#....#..#..##.#.............#.....#...##......................#............................##.......#........#.........\n.#......................................#........#.....#..............................................#...................#..#.....\n...###.#.....#...................#..........................................#..##.......#..#...................#...................\n.....................#.#...........##.....#........#...#......................###...........................#......................\n...............#..................#...........#....#...............................#.....#...............................#.........\n......#..........#.##....#.......#.#....................................................................###......#....#............\n...........#....#..............#....................#....................................#......#.......#..........#.........#...#.\n....##.........##..#.........#...............#....................#...............#.....#.##.....#............#.....#.#............\n...#..#..........#............#.....#....#...##...#....................#.............#.....#.....#...#...................#.........\n....#.............#.....#...#...#...........##.................#..................#.#...........#...........##.........#...........\n......#............................#..........................................................#...#......#..#...........#..........\n...........................#...........#.............................................#.....#..#...........#......................#.\n.#..#...#..##.##............#...##..............................#....................#................#.............#....#.........\n......................#...........#....................#..............................#..................#.......#.................\n...........#.......#................#.....#.#.............#.#......#.................................##..#......................#..\n...............#......#....................#...........#..................................#.....#..#............#.......#.#....#...\n..#...........#.#.......................................#...#........#..#................#..............#..#.#.......#........#....\n......................#...#..........................................................................#........#....................\n.............#.............##...#...........................#..#....#.....................#..#.......#...........#.................\n.#....................#......#.....#....#.......#.............#...##..............#........#.#....#..#..............#......#..#....\n....#.......#...............##.................#.................................................#........#....#....#..............\n.#.............#....#..........................#................................................#.............#.##.................\n..#........................#...........................................#............#........#.........#..#.................#......\n......................#.............#...............#.........#........##......#.#.......................#.........#...#...........\n..#...........#..............#..............#...........#......#.........#...#.....#.......................#...#.#.................\n...##..#.........#...............#....................#..#..#..#.....#..............#...#..............#.#...#......#.#............\n.......................#.............................#....#...#............#..#...................................#..............#.\n.#...#.##..........#..##.#.......................#........#.....#...................................#.#...........#....#..##....#..\n..............#.#....#.......#...........#.........#......#....................#......##............#..............................\n..............#..........#............#..........#.....#....#.............................#.#.......#.....#.....#..........#.......\n..#.....#....#..........#.....................##..#....##..#..##......#....................................#..................#....\n...................#..#...............##...............#.#....#..................##.......................#........#...........#...\n....#...#..................#................................#......#...#.....#...........#................................#........\n....................................#...........#..#......##.......#..#.................#..#.......................................\n............#....#....#............#.#.................#........................#...............#............#..............#......\n................................#............#..................#.##.....#.....................#............###...........#...#.#..\n.............#.........#.........#.................#..................##....#..........#..#..............................#.#.......\n..........................................#................#........#..........#............#...........................#....##..#.\n.#...#...#.....##...........................#.............#..............................#..#.................#..#....#.........##.\n............#...............#.....#..#.....#.................#........#..#.......#........#...##.#...............#.......#..#...#..\n..#.#.#.........#..........#............#..##....#......###........#.#......#....#..#.....#.......#........................#.......\n.............#....................#.#.#.............#...#.#.....#..#....#.#...#....#....#.......#.#....................#...#.......\n......##..................#............#....................#...................#....#.........#.#.........................#..#....\n............#.##.........#...............#...........................#..............#.#............................#...............\n........#....#...............#.....#..#......#...##....#............#.....#.........##.....................#..................#....\n.................................##....#..#.#.......#........#.................#.#.........................#...........#.#.#.......\n........................#....#............................#..#.....#.....#.#...........................................#...........\n.#.......#...........#....#......................#.........#......#...#...#.......#.#..........##.....#................#...........\n......#...........................#......#.#.......#.......#.#........................#..................#..............#..........\n........#.........#........#..#...................#...#...#...#......#.#................##.#......#.......#...............#..#..##.\n.......#........................#..........##.........#...##..............#.....#.....#............................................\n.......#................#....##.......................#..#..................#....................#.............#.............#.....\n............................#...#...#........##........##..........#.......#..............#......................................#.\n......#............................................#.........#......#....................#.....#.##.#.............#................\n...............#...........##......#..........................#...........#..............................#.#....#.#..........#..#..\n........................##..................................................#.......................#........#.....#...............\n....................#..............#..............#.............#.......#..........................#.............#.................\n.................#..#.#.#......#.........#.....#...........#.......#..........#...........#........................................\n.................................................#.............................................#..........#....#..##...#.........#.\n...................#....#.................#.......#...#............#....................#.............#...............#............\n.........#....#......#......#...#...#.......#.......#..#.............#....#.....#..............#....#...................#..........\n.........#..#..............................#....#.......#.......#....#.....#...#...#...#...........#.....##...............#........\n.....#..................#....#........#............##.#....#..............#...#.#.....#...........#.#......#....#..................\n.................................................................S.................................................................\n.......#...........#.#.........#...#........#.#......#.......##.#......##...........................#...#.....#.........#..........\n..................................................#............................#..........#................###......##..#..........\n........#....#.......................#.##...#......#...........#..............#......#............#................................\n.........................#...........................#.................#....#..#................#....................#.............\n...................#..................#.........................#........##....#.................##..#..#.......##.....#...........\n...............................#..#........#.#........#..............#............#..##...#.#.......#..............................\n...............#.............#...#.....#.........#..##............................#..............#.#........#..#...#...............\n..#.........#................#.......##...............#...............#........#......#.......#...........##...#.#..#...........#..\n.............#............#....##..#.#......##...##..#................................#..#.....##....#........................#....\n..............#.....#...#.....#...................#.......##.#.......#..#..............................#.....#.....................\n........................#......#...#......#.....#...........#.#...#...................#........#..........#..#.....................\n...................#..................#.......#......................................##......#...#..#........##....................\n.....................#......................#.........#.#.#.............#.....#...........#...#..........#.........................\n.........................#.#...#..........#....##.............................#........#......#...#.........#......................\n.#......#.#...............#.#.#.#.............#...#...#...............##..#...........#...#..........#.#.#...#...................#.\n........#.###...........#..#..........##.....#.#.........#.#..#..............#..............#..........................#.....#.....\n......#........................................#......#.........#...#..............................#.....................#.....##..\n....#...#.....................#....#..........#.........................#....#.#..........#..#...#..................#.......#......\n...#......#..............#.....................#..........................#...........#.....#....#...#.............................\n........#.......#.........#................#...........#......##......................................#...................#.##.....\n..#..#..#...................#..................#.........#...#......#............#..#.#.#.........#..#.............................\n.........##..##...........................#.........#.....................#.......#.#...#...#.......#................#.#...........\n.....#.......#..............#...#..................#.................................#..#..#......#...#..............#........#....\n............................#.............#.................................#..#..#...#................................#..#........\n........#.#....#.............#.#............#..............##.......###............................#..........#..........#.........\n.......#...#....................#....#.#....#...#.#.#...##.........................#..........................................#....\n..#......................................................###.........................#...............................#.##..........\n......#........#...#..............#......#...............#...##.#...#.........#.........#.........#...................##...........\n.........#.....#..................#............#.....#........#........#..................#.#.............#........#....#..........\n...##...............#...#...........#..##...........#...#.#................##.......#....#.#....#...........#........#.#...........\n......#.............#...................##..#................#................#..........#...#..........#.......#...........#......\n.......#................................................#..............#..........#.#......#..#........#....#....#.#...#...........\n....#.....#.........#...#....#.........................#..#.............##.....#.#...............................#.#.....#.........\n.......................................#.....##.....#...#.#......................#..#................................#...........#.\n......#..........##.#..........................................#.......##..#.........##........................#................#..\n..............#.......#........................#.......#.#......#...............#.#.................#.............#..#.............\n....................................................#...........#.....#......#.#.#................##....#...#.#.#.........#........\n........#..................#.................................##.....................#...#............##.....#.#.........#...#...#..\n.....#....#.#...#......#......#.........................#.#...............#..#.......................#...........#..##.........#.#.\n..........#.................................#.....................#...#.#......#.....##...........#..............#.................\n..##..##.....................#..................#.#......#.#.......#....#.#..........................#.#...#.........#...#.........\n...................#.......#...#.....................................#...#........#....................#.............#.......#.....\n............#..#..#...................................#......#..................#..........#..........##....................#......\n...........##.........#...#.#.....#....#............##...#.............................................#..#.....#..........#.......\n......#....#..............#.......#..................#...##...#.#.......#..........................#...#..............##...........\n............#..##....#...........#..#....##...........#........................................#.....#..#..#........#..............\n....................#.....#.#....#.........#.........#.......................................................#.........#....#......\n.........#...#...................#........................#..................#................#............#.#.....................\n.......................#.......#..........................#..#........................#.........#..................#....#..........\n...#.#.................................#..#...................#......#.....#.......................#......#.......#.........#......\n...#............#.....#...#.....#.....#.#................#....#....#.#...#................#...............#...............#....#...\n...............................#.........................####.#...#...#...............................#.........................##.\n.....#.................#..#..##.....#...#....................##....................#.#........#................#.#...........#.....\n.#.............#..#.........#.###.#...........#............#....................#........................#......#....###..#........\n......#.......#..#.........#......................##..............................#...................#.......#......#....#........\n....#.....#.......................#.........#.....................#................#..............#....................#......#....\n......#............#...#...#....#.#.................#...............#...................#..........#.............#..#.#............\n......................#............................#...................................#.#.#...#.#...#........#..........#....#..#.\n......#......................#..............#.......#........................#.............##.#.#..................................\n..................................#............##..........................#......#......#..#...............#......................\n......#.........#..##.#...##......#............#..........................#.......#........#....##...#...#.........................\n.#....................#.........#.........#.................................##...............##...........#............#...#.......\n..#..................#.....#.......#..#.........#.....#..###..................#.......#....#.............##.#..#...................\n.#.....#...#.#.............#.....#.....#..#.....#.........#...........#...#......#............#..#.#.......#......#................\n...................................................................................................................................\n",
  "brief": {
    "first": "You manage to catch the [airship](7) right as it's dropping someone else off on their all-expenses-paid trip to Desert Island! It even helpfully drops you off near the [gardener](5) and his massive farm.\n\n\"You got the sand flowing again! Great work! Now we just need to wait until we have enough sand to filter the water for Snow Island and we'll have snow again in no time.\"\n\nWhile you wait, one of the Elves that works with the gardener heard how good you are at solving problems and would like your help. He needs to get his [steps](https://en.wikipedia.org/wiki/Pedometer) in for the day, and so he'd like to know *which garden plots he can reach with exactly his remaining `64` steps*.\n\nHe gives you an up-to-date map (your puzzle input) of his starting position (`S`), garden plots (`.`), and rocks (`#`). For example:\n\n```\n...........\n.....###.#.\n.###.##..#.\n..#.#...#..\n....#.#....\n.##..S####.\n.##..#...#.\n.......##..\n.##.#.####.\n.##..##.##.\n...........\n\n```\n\nThe Elf starts at the starting position (`S`) which also counts as a garden plot. Then, he can take one step north, south, east, or west, but only onto tiles that are garden plots. This would allow him to reach any of the tiles marked `O`:\n\n```\n...........\n.....###.#.\n.###.##..#.\n..#.#...#..\n....#O#....\n.##.OS####.\n.##..#...#.\n.......##..\n.##.#.####.\n.##..##.##.\n...........\n\n```\n\nThen, he takes a second step. Since at this point he could be at *either* tile marked `O`, his second step would allow him to reach any garden plot that is one step north, south, east, or west of *any* tile that he could have reached after the first step:\n\n```\n...........\n.....###.#.\n.###.##..#.\n..#.#O..#..\n....#.#....\n.##O.O####.\n.##.O#...#.\n.......##..\n.##.#.####.\n.##..##.##.\n...........\n\n```\n\nAfter two steps, he could be at any of the tiles marked `O` above, including the starting position (either by going north-then-south or by going west-then-east).\n\nA single third step leads to even more possibilities:\n\n```\n...........\n.....###.#.\n.###.##..#.\n..#.#.O.#..\n...O#O#....\n.##.OS####.\n.##O.#...#.\n....O..##..\n.##.#.####.\n.##..##.##.\n...........\n\n```\n\nHe will continue like this until his steps for the day have been exhausted. After a total of `6` steps, he could reach any of the garden plots marked `O`:\n\n```\n...........\n.....###.#.\n.###.##.O#.\n.O#O#O.O#..\nO.O.#.#.O..\n.##O.O####.\n.##.O#O..#.\n.O.O.O.##..\n.##.#.####.\n.##O.##.##.\n...........\n\n```\n\nIn this example, if the Elf's goal was to get exactly `6` more steps today, he could use them to reach any of `*16*` garden plots.\n\nHowever, the Elf *actually needs to get `64` steps today*, and the map he's handed you is much larger than the example map.\n\nStarting from the garden plot marked `S` on your map, *how many garden plots could the Elf reach in exactly `64` steps?*\n\nYour puzzle answer was `3853`.\n\nThe first half of this puzzle is complete! It provides one gold star: \\*\n\n\\--- Part Two ---\n----------\n\nThe Elf seems confused by your answer until he realizes his mistake: he was reading from a list of his favorite numbers that are both perfect squares and perfect cubes, not his step counter.\n\nThe *actual* number of steps he needs to get today is exactly `*26501365*`.\n\nHe also points out that the garden plots and rocks are set up so that the map *repeats infinitely* in every direction.\n\nSo, if you were to look one additional map-width or map-height out from the edge of the example map above, you would find that it keeps repeating:\n\n```\n.................................\n.....###.#......###.#......###.#.\n.###.##..#..###.##..#..###.##..#.\n..#.#...#....#.#...#....#.#...#..\n....#.#........#.#........#.#....\n.##...####..##...####..##...####.\n.##..#...#..##..#...#..##..#...#.\n.......##.........##.........##..\n.##.#.####..##.#.####..##.#.####.\n.##..##.##..##..##.##..##..##.##.\n.................................\n.................................\n.....###.#......###.#......###.#.\n.###.##..#..###.##..#..###.##..#.\n..#.#...#....#.#...#....#.#...#..\n....#.#........#.#........#.#....\n.##...####..##..S####..##...####.\n.##..#...#..##..#...#..##..#...#.\n.......##.........##.........##..\n.##.#.####..##.#.####..##.#.####.\n.##..##.##..##..##.##..##..##.##.\n.................................\n.................................\n.....###.#......###.#......###.#.\n.###.##..#..###.##..#..###.##..#.\n..#.#...#....#.#...#....#.#...#..\n....#.#........#.#........#.#....\n.##...####..##...####..##...####.\n.##..#...#..##..#...#..##..#...#.\n.......##.........##.........##..\n.##.#.####..##.#.####..##.#.####.\n.##..##.##..##..##.##..##..##.##.\n.................................\n\n```\n\nThis is just a tiny three-map-by-three-map slice of the inexplicably-infinite farm layout; garden plots and rocks repeat as far as you can see. The Elf still starts on the one middle tile marked `S`, though - every other repeated `S` is replaced with a normal garden plot (`.`).\n\nHere are the number of reachable garden plots in this new infinite version of the example map for different numbers of steps:\n\n* In exactly `6` steps, he can still reach `*16*` garden plots.\n* In exactly `10` steps, he can reach any of `*50*` garden plots.\n* In exactly `50` steps, he can reach `*1594*` garden plots.\n* In exactly `100` steps, he can reach `*6536*` garden plots.\n* In exactly `500` steps, he can reach `*167004*` garden plots.\n* In exactly `1000` steps, he can reach `*668697*` garden plots.\n* In exactly `5000` steps, he can reach `*16733044*` garden plots.\n\nHowever, the step count the Elf needs is much larger! Starting from the garden plot marked `S` on your infinite map, *how many garden plots could the Elf reach in exactly `26501365` steps?*\n\nAnswer:\n\nAlthough it hasn't changed, you can still [get your puzzle input](21/input)."
  }
}